{
    "intro_text" : {
        "a0" : "В Генсокё разразилась таинственная буря.",
        "a1" : "Из ниоткуда появился таинственный концерт. Он привлекает различных обитателей Генсокё.",
        "a2" : "Две местные музыкальные группы возмущены тем, что их аудитория была вытеснена загадочным концертом.",
        "a3" : "И вот они обращаются за помощью к самой влиятельной женщине Генсокё.",
        "a4" : "Когда Рейму Хакурей узнала об этой странной буре, она решает отправиться на поиски её источника.",
        "a5" : " "
    }
}